opencv_extra/__init__.py
opencv_extra/text_utils.py
opencv_extra-1.0.3.dist-info/METADATA
opencv_extra-1.0.3.dist-info/WHEEL
opencv_extra-1.0.3.dist-info/licenses/LICENSE
opencv_extra-1.0.3.dist-info/RECORD
