Metadata-Version: 2.4
Name: opencv_extra
Version: 1.0.3
Summary: This package is built as a opencv utilities. Additional algorithms to write text and making boxes on the image.
Author-email: "M. Rayyan Akhtar" <akhtar.rayyan@live.com>
License-File: LICENSE
Classifier: License :: OSI Approved :: MIT License
Classifier: Operating System :: OS Independent
Classifier: Programming Language :: Python :: 3
Requires-Python: >=3.8
